{
  "example_product_1": {
    "site": "example_product_1",
    "url": "https://www.example.com/product/123",
    "scraped_at": "2026-05-03T01:26:57.782056",
    "success": true,
    "data": {
      "title": "Example Domain",
      "price": null,
      "description": null
    }
  },
  "example_product_2": {
    "site": "example_product_2",
    "url": "https://www.example.com/product/456",
    "scraped_at": "2026-05-03T01:27:00.990438",
    "success": true,
    "data": {
      "title": "Example Domain",
      "price": null,
      "description": null
    }
  }
}